aiapi/__init__.py
aiapi/formatConversion.py
aiapi-0.0.2.dist-info/METADATA
aiapi-0.0.2.dist-info/WHEEL
aiapi-0.0.2.dist-info/top_level.txt
aiapi-0.0.2.dist-info/RECORD
