Metadata-Version: 2.1
Name: aiapi
Version: 0.0.2
Summary: aiapi 官方sdk包
Home-page: http://aiapi.pro
Author: aiapi@admin
Author-email: j0hn.wahahaha@gmail.com
License: UNKNOWN
Platform: UNKNOWN
Classifier: Programming Language :: Python :: 3
Classifier: License :: OSI Approved :: MIT License
Classifier: Operating System :: OS Independent
